{"nodes": [{"id": "c_users_pc_desktop_dukkan_app_telefon_takip_v2_telefon_takip_v2_src_components_ui_sortable_header_tsx", "label": "sortable-header.tsx", "file_type": "code", "source_file": "C:\\Users\\PC\\Desktop\\dukkan-app\\telefon-takip-v2\\telefon-takip-v2\\src\\components\\ui\\sortable-header.tsx", "source_location": "L1"}, {"id": "ui_sortable_header_sortableheaderprops", "label": "SortableHeaderProps", "file_type": "code", "source_file": "C:\\Users\\PC\\Desktop\\dukkan-app\\telefon-takip-v2\\telefon-takip-v2\\src\\components\\ui\\sortable-header.tsx", "source_location": "L7"}, {"id": "ui_sortable_header_sortableheader", "label": "SortableHeader()", "file_type": "code", "source_file": "C:\\Users\\PC\\Desktop\\dukkan-app\\telefon-takip-v2\\telefon-takip-v2\\src\\components\\ui\\sortable-header.tsx", "source_location": "L17"}], "edges": [{"source": "c_users_pc_desktop_dukkan_app_telefon_takip_v2_telefon_takip_v2_src_components_ui_sortable_header_tsx", "target": "lucide_react", "relation": "imports_from", "context": "import", "confidence": "EXTRACTED", "source_file": "C:\\Users\\PC\\Desktop\\dukkan-app\\telefon-takip-v2\\telefon-takip-v2\\src\\components\\ui\\sortable-header.tsx", "source_location": "L3", "weight": 1.0}, {"source": "c_users_pc_desktop_dukkan_app_telefon_takip_v2_telefon_takip_v2_src_components_ui_sortable_header_tsx", "target": "c_users_pc_desktop_dukkan_app_telefon_takip_v2_telefon_takip_v2_src_lib_utils_ts", "relation": "imports_from", "context": "import", "confidence": "EXTRACTED", "source_file": "C:\\Users\\PC\\Desktop\\dukkan-app\\telefon-takip-v2\\telefon-takip-v2\\src\\components\\ui\\sortable-header.tsx", "source_location": "L4", "weight": 1.0}, {"source": "c_users_pc_desktop_dukkan_app_telefon_takip_v2_telefon_takip_v2_src_components_ui_sortable_header_tsx", "target": "lib_utils_cn", "relation": "imports", "context": "import", "confidence": "EXTRACTED", "source_file": "C:\\Users\\PC\\Desktop\\dukkan-app\\telefon-takip-v2\\telefon-takip-v2\\src\\components\\ui\\sortable-header.tsx", "source_location": "L4", "weight": 1.0}, {"source": "c_users_pc_desktop_dukkan_app_telefon_takip_v2_telefon_takip_v2_src_components_ui_sortable_header_tsx", "target": "c_users_pc_desktop_dukkan_app_telefon_takip_v2_telefon_takip_v2_src_hooks_use_table_sort_ts", "relation": "imports_from", "context": "import", "confidence": "EXTRACTED", "source_file": "C:\\Users\\PC\\Desktop\\dukkan-app\\telefon-takip-v2\\telefon-takip-v2\\src\\components\\ui\\sortable-header.tsx", "source_location": "L5", "weight": 1.0}, {"source": "c_users_pc_desktop_dukkan_app_telefon_takip_v2_telefon_takip_v2_src_components_ui_sortable_header_tsx", "target": "hooks_use_table_sort_sortorder", "relation": "imports", "context": "import", "confidence": "EXTRACTED", "source_file": "C:\\Users\\PC\\Desktop\\dukkan-app\\telefon-takip-v2\\telefon-takip-v2\\src\\components\\ui\\sortable-header.tsx", "source_location": "L5", "weight": 1.0}, {"source": "c_users_pc_desktop_dukkan_app_telefon_takip_v2_telefon_takip_v2_src_components_ui_sortable_header_tsx", "target": "ui_sortable_header_sortableheaderprops", "relation": "contains", "confidence": "EXTRACTED", "source_file": "C:\\Users\\PC\\Desktop\\dukkan-app\\telefon-takip-v2\\telefon-takip-v2\\src\\components\\ui\\sortable-header.tsx", "source_location": "L7", "weight": 1.0}, {"source": "c_users_pc_desktop_dukkan_app_telefon_takip_v2_telefon_takip_v2_src_components_ui_sortable_header_tsx", "target": "ui_sortable_header_sortableheader", "relation": "contains", "confidence": "EXTRACTED", "source_file": "C:\\Users\\PC\\Desktop\\dukkan-app\\telefon-takip-v2\\telefon-takip-v2\\src\\components\\ui\\sortable-header.tsx", "source_location": "L17", "weight": 1.0}], "raw_calls": [{"caller_nid": "ui_sortable_header_sortableheader", "callee": "cn", "is_member_call": false, "source_file": "C:\\Users\\PC\\Desktop\\dukkan-app\\telefon-takip-v2\\telefon-takip-v2\\src\\components\\ui\\sortable-header.tsx", "source_location": "L30"}]}